selenium_browser_desktop_recorder.py
pydesktopbrowserrecorder-0.0.6.dist-info/LICENSE
pydesktopbrowserrecorder-0.0.6.dist-info/METADATA
pydesktopbrowserrecorder-0.0.6.dist-info/WHEEL
pydesktopbrowserrecorder-0.0.6.dist-info/top_level.txt
pydesktopbrowserrecorder-0.0.6.dist-info/RECORD
