Metadata-Version: 2.1
Name: pydesktopbrowserrecorder
Version: 0.0.6
Summary: Module to record videos of an automation session using Selenium webdriver or the desktop.
Home-page: https://github.com/AntoData/PyDesktopBrowserRecorder
Author: Antonio Pérez
Author-email: ingovanpe@gmail.com
License: UNKNOWN
Platform: UNKNOWN
Classifier: Programming Language :: Python :: 3
Classifier: License :: OSI Approved :: MIT License
Classifier: Operating System :: OS Independent
Requires-Python: >=3.10
License-File: LICENSE
